vijay_lib/__init__.py
vijay_lib/iqr.py
vijay_lib-0.7.0.dist-info/LICENSE
vijay_lib-0.7.0.dist-info/METADATA
vijay_lib-0.7.0.dist-info/WHEEL
vijay_lib-0.7.0.dist-info/top_level.txt
vijay_lib-0.7.0.dist-info/RECORD
