Metadata-Version: 2.1
Name: vijay-lib
Version: 0.7.0
Summary: A library to calculate upper and lower IQR values.
Home-page: https://github.com/yourusername/vijay_lib
Author: Vijayraje Jadhav
Author-email: jadhavvijayraje1137@gmail.com
License: UNKNOWN
Platform: UNKNOWN
Classifier: Programming Language :: Python :: 3
Classifier: License :: OSI Approved :: MIT License
Classifier: Operating System :: OS Independent
Requires-Python: >=3.6
License-File: LICENSE
Requires-Dist: numpy
